shodo/__init__.py
shodo/api.py
shodo/conf.py
shodo/lint.py
shodo/main.py
shodo/py.typed
shodo/aio/__init__.py
shodo/aio/api.py
shodo/aio/lint.py
tests/__init__.py
tests/test_conf.py
tests/test_main.py
tests/test_aio/__init__.py
tests/test_aio/test_lint.py
shodo-1.1.0.dist-info/LICENSE
shodo-1.1.0.dist-info/METADATA
shodo-1.1.0.dist-info/WHEEL
shodo-1.1.0.dist-info/entry_points.txt
shodo-1.1.0.dist-info/top_level.txt
shodo-1.1.0.dist-info/RECORD
