Metadata-Version: 2.1
Name: shodo
Version: 1.1.0
Summary: Shodo Python CLI
Home-page: https://github.com/zenproducts/shodo-python
Author: ZenProducts Inc.
License: MIT
Classifier: Programming Language :: Python :: 3
Classifier: Development Status :: 5 - Production/Stable
Classifier: License :: OSI Approved :: MIT License
Requires-Python: >=3.8
License-File: LICENSE
Requires-Dist: Click
Requires-Dist: requests
Provides-Extra: async
Requires-Dist: aiohttp ; extra == 'async'
Provides-Extra: dev
Requires-Dist: aioresponses ; extra == 'dev'
Requires-Dist: pytest ; extra == 'dev'
Requires-Dist: pytest-asyncio ; extra == 'dev'
Requires-Dist: pytest-mock ; extra == 'dev'
Requires-Dist: pytest-responses ; extra == 'dev'
Requires-Dist: mypy ; extra == 'dev'
Requires-Dist: types-requests ; extra == 'dev'
